mtmlib/__init__.py
mtmlib/dbUtils.py
mtmlib/decorators/mtform/__init__.py
mtmlib/decorators/mtform/mtform.py
mtmlib/env.py
mtmlib/github.py
mtmlib/httpUtils.py
mtmlib/logging.py--
mtmlib/mtutils.py
mtmlib/queue/__init__.py
mtmlib/queue/mtqueue_client.py
mtmlib/queue/queue.py
mtmlib/rproxy.py
mtmlib/tunnel.py
mtmlib/vercel.py
mtmlib/version_tag.py
mtmlib-0.4.202.dist-info/METADATA
mtmlib-0.4.202.dist-info/WHEEL
mtmlib-0.4.202.dist-info/RECORD
