Metadata-Version: 2.1
Name: mtmlib
Version: 0.4.202
Summary: 
License: MIT
Author: John Smith
Author-email: john@example.com
Requires-Python: >=3.10,<3.13
Classifier: License :: OSI Approved :: MIT License
Classifier: Programming Language :: Python :: 3
Classifier: Programming Language :: Python :: 3.10
Classifier: Programming Language :: Python :: 3.11
Classifier: Programming Language :: Python :: 3.12
Requires-Dist: beautifulsoup4 (>=4.12.2)
Requires-Dist: colorama (>=0.4.6,<0.5.0)
Requires-Dist: email-validator (>=2.2.0,<3.0.0)
Requires-Dist: emails (>=0.6,<0.7)
Requires-Dist: fastapi (>=0.104.1)
Requires-Dist: httpx (>=0.27.0,<0.28.0)
Requires-Dist: jinja2 (>=3.1.4,<4.0.0)
Requires-Dist: json_repair (>=0.25.2)
Requires-Dist: langchain-core (>=0.3.6,<0.4.0)
Requires-Dist: langchain_community (>=0.3,<0.4)
Requires-Dist: langgraph (>=0.2.13)
Requires-Dist: markdown (>=3.6,<4.0)
Requires-Dist: nanoid (>=2.0.0,<3.0.0)
Requires-Dist: pgvector (>=0.3.2,<0.4.0)
Requires-Dist: pillow (>=10.4.0,<11.0.0)
Requires-Dist: psycopg (>=3.2.1)
Requires-Dist: psycopg_pool (>=3.2.2)
Requires-Dist: pydantic (>=2.5.1)
Requires-Dist: pygithub (>=2.3.0,<3.0.0)
Requires-Dist: pyjwt (>=2.9.0,<3.0.0)
Requires-Dist: python-dotenv (>=1.0.0)
Requires-Dist: python-logging-loki (>=0.3.1,<0.4.0)
Requires-Dist: python-multipart (>=0.0.6)
Requires-Dist: sqlmodel (>=0.0.21,<0.0.22)
Requires-Dist: wikipedia (>=1.4.0,<2.0.0)
